janitor/__init__.py
janitor/cli.py
janitor/constants.py
janitor/module/__init__.py
janitor/module/clean.py
janitor/module/history.py
janitor/module/util.py
janitor/provider/__init__.py
janitor/provider/openstack.py
janitor_osp-0.5.post1.dist-info/AUTHORS
janitor_osp-0.5.post1.dist-info/LICENSE
janitor_osp-0.5.post1.dist-info/METADATA
janitor_osp-0.5.post1.dist-info/WHEEL
janitor_osp-0.5.post1.dist-info/entry_points.txt
janitor_osp-0.5.post1.dist-info/top_level.txt
janitor_osp-0.5.post1.dist-info/RECORD
