Metadata-Version: 2.1
Name: janitor-osp
Version: 0.5.post1
Summary: Linux cli tool to maintain Openstack quota, deleting old virtual machines, volumes and IP
Home-page: https://github.com/eduardocerqueira/janitor.git
Author: Eduardo Cerqueira
Author-email: eduardomcerqueira@gmail.com
License: GPL
Platform: UNKNOWN
Requires-Python: >=3
Requires-Dist: click
Requires-Dist: PrettyTable (<0.8,>=0.7.1)
Requires-Dist: python-openstackclient
Requires-Dist: python-neutronclient
Requires-Dist: python-novaclient
Requires-Dist: python-glanceclient
Requires-Dist: python-cinderclient
Requires-Dist: pyrsistent (==0.16.1)
Requires-Dist: decorator (==4.4.2)
